{
  "eventJumbotron": {
    "title": "OUR EVENTS",
    "description": "Lorem ipsum dolor sit amet consectetur adipisicing elit. Minima vel id aliquam, aspernatur voluptate culpa mollitia aperiam similique harum doloremque provident illo laboriosam aliquid doloribus dolor cum cupiditate maxime quo ad reprehenderit necessitatibus consequatur at, dicta consectetur. Cum ex veniam ullam alias harum sed nemo reiciendis. Fugiat dolor nemo, quas est mollitia aperiam cupiditate eligendi porro.",
    "image": "https://source.unsplash.com/an-aerial-view-of-a-field-with-trees-kuy1a_lU-hA"
  },
  "blogsJumbotron": {
    "title": "OUR BLOGS",
    "description": "Lorem ipsum dolor sit amet consectetur adipisicing elit. Minima vel id aliquam, aspernatur voluptate culpa mollitia aperiam similique harum doloremque provident illo laboriosam aliquid doloribus dolor cum cupiditate maxime quo ad reprehenderit necessitatibus consequatur at, dicta consectetur. Cum ex veniam ullam alias harum sed nemo reiciendis. Fugiat dolor nemo, quas est mollitia aperiam cupiditate eligendi porro.",
    "image": "https://source.unsplash.com/low-angle-photography-of-trees-during-night-time-_OQ8Jc7kBmA"
  }
}
